[{"ProductId":2053,"Reference":null,"SkuProduct":null,"ProductName":"Vente karim","ProductDescription":null,"ProductQuantity":0,"StartDate":"2018-07-28T00:00:00","StartHour":0,"EndDate":"2018-07-28T00:00:00","ImagePath":"http://kids-privee.com/Images/AZERTYU-0-tops-t-shirts-imprime (1).jpg","Image":{"ProductId":0,"ProductSubUniverId":0,"ProductDetailId":0,"Reference":null,"ImageId":0,"ImageTypeId":0,"ImagePath":null,"PathRedirect":null,"ImageLinkPath":null,"Price":0.0,"OldPrice":0.0,"Desctption":null,"Color":null,"Composition":null},"ImageUniver":{"ProductId":0,"ProductSubUniverId":0,"ProductDetailId":0,"Reference":null,"ImageId":0,"ImageTypeId":0,"ImagePath":null,"PathRedirect":null,"ImageLinkPath":null,"Price":0.0,"OldPrice":0.0,"Desctption":null,"Color":null,"Composition":null},"IsToM":true,"IsFlash":true}]